redturtle.bandi-1.6.1-py3.11-nspkg.pth
redturtle/bandi/README.txt
redturtle/bandi/__init__.py
redturtle/bandi/config.py
redturtle/bandi/configure.zcml
redturtle/bandi/indexer.py
redturtle/bandi/psheetvocabulary.py
redturtle/bandi/testing.py
redturtle/bandi/upgrades.py
redturtle/bandi/upgrades.zcml
redturtle/bandi/vocabularies.py
redturtle/bandi/browser/__init__.py
redturtle/bandi/browser/bando-right.pt
redturtle/bandi/browser/bando.pt
redturtle/bandi/browser/bando.py
redturtle/bandi/browser/collection.pt
redturtle/bandi/browser/collection.py
redturtle/bandi/browser/configure.zcml
redturtle/bandi/browser/context.py
redturtle/bandi/browser/controlpanel.py
redturtle/bandi/browser/migrator.py
redturtle/bandi/browser/search.pt
redturtle/bandi/browser/search.py
redturtle/bandi/browser/search_form.pt
redturtle/bandi/browser/searchbandi.js
redturtle/bandi/browser/css/Makefile
redturtle/bandi/browser/css/bandi.css
redturtle/bandi/browser/css/bandi.css.map
redturtle/bandi/browser/css/bandi.scss
redturtle/bandi/browser/images/bando.png
redturtle/bandi/browser/images/bando_closed.png
redturtle/bandi/browser/images/bando_icon.svg
redturtle/bandi/browser/images/bando_inprogress.png
redturtle/bandi/browser/images/bando_open.png
redturtle/bandi/browser/images/folder_bando_deep.gif
redturtle/bandi/content/__init__.py
redturtle/bandi/content/bando.py
redturtle/bandi/content/bandofolderdeepening.py
redturtle/bandi/content/configure.zcml
redturtle/bandi/interfaces/__init__.py
redturtle/bandi/interfaces/bando.py
redturtle/bandi/interfaces/bandoSchema.py
redturtle/bandi/interfaces/bandofolderdeepening.py
redturtle/bandi/interfaces/bandofolderdeepeningschema.py
redturtle/bandi/interfaces/browserlayer.py
redturtle/bandi/interfaces/settings.py
redturtle/bandi/locales/manual.pot
redturtle/bandi/locales/redturtle.bandi.pot
redturtle/bandi/locales/update.py
redturtle/bandi/locales/update.sh
redturtle/bandi/locales/it/LC_MESSAGES/plone.po
redturtle_bandi-1.6.1.dist-info/METADATA
redturtle_bandi-1.6.1.dist-info/WHEEL
redturtle_bandi-1.6.1.dist-info/entry_points.txt
redturtle_bandi-1.6.1.dist-info/namespace_packages.txt
redturtle_bandi-1.6.1.dist-info/top_level.txt
redturtle_bandi-1.6.1.dist-info/RECORD
