Metadata-Version: 2.4
Name: redturtle.bandi
Version: 1.6.1
Summary: A product for announcements management based on rer.bandi
Home-page: https://github.com/PloneGov-IT/redturtle.bandi
Author: RedTurtle Technology
Author-email: sviluppoplone@redturtle.it
License: GPL
Project-URL: PyPI, https://pypi.python.org/pypi/redturtle.bandi
Project-URL: Source, https://github.com/RedTurtle/redturtle.bandi
Project-URL: Tracker, https://github.com/RedTurtle/redturtle.bandi/issues
Keywords: redturtle bandi announcements
Classifier: Development Status :: 5 - Production/Stable
Classifier: Environment :: Web Environment
Classifier: Framework :: Plone :: 5.2
Classifier: Framework :: Plone :: 6.0
Classifier: Framework :: Plone :: Addon
Classifier: Framework :: Plone
Classifier: License :: OSI Approved :: GNU General Public License v2 (GPLv2)
Classifier: Operating System :: OS Independent
Classifier: Programming Language :: Python :: 3.8
Classifier: Programming Language :: Python :: 3.11
Classifier: Programming Language :: Python
Requires-Python: >=3.8
Requires-Dist: setuptools
Requires-Dist: lxml
Requires-Dist: plone.restapi
Requires-Dist: collective.tiles.collection
Provides-Extra: test
Requires-Dist: plone.app.testing; extra == "test"
Requires-Dist: plone.testing>=5.0.0; extra == "test"
Requires-Dist: plone.app.contenttypes; extra == "test"
Requires-Dist: plone.app.robotframework[debug]; extra == "test"
Requires-Dist: collective.MockMailHost; extra == "test"
Dynamic: author
Dynamic: author-email
Dynamic: classifier
Dynamic: description
Dynamic: home-page
Dynamic: keywords
Dynamic: license
Dynamic: project-url
Dynamic: provides-extra
Dynamic: requires-dist
Dynamic: requires-python
Dynamic: summary
